Metadata-Version: 2.2
Name: dind
Version: 0.1
Summary: library to import popular data librabries
Home-page: https://github.com/owlpharoah/dind
Author: owlpharoah
Author-email: sreeharirathish128@gmail.com
Classifier: Programming Language :: Python :: 3
Classifier: Operating System :: OS Independent
Requires-Python: >=3.6
Requires-Dist: numpy
Requires-Dist: pandas
Requires-Dist: matplotlib.pyplot
Dynamic: author
Dynamic: author-email
Dynamic: classifier
Dynamic: description
Dynamic: description-content-type
Dynamic: home-page
Dynamic: requires-dist
Dynamic: requires-python
Dynamic: summary
